MANIFEST.in
README.md
setup.cfg
setup.py
aa2atom/__init__.py
aa2atom/aa2atom.py
aa2atom/atom2mass.py
aa2atom/devel.py
aa2atom/formulas.py
aa2atom/isotopes.py
aa2atom/ptms.py
aa2atom/test_aa2atom.py
aa2atom.egg-info/PKG-INFO
aa2atom.egg-info/SOURCES.txt
aa2atom.egg-info/dependency_links.txt
aa2atom.egg-info/top_level.txt
bin/aa2atom
bin/aa2mass
bin/atom2mass