Metadata-Version: 1.1
Name: aa2atom
Version: 1.23
Summary: Change amino-acidic sequence into counts of atoms.
Home-page: UNKNOWN
Author: Mateusz Krzysztof Łącki
Author-email: matteo.lacki@gmail.com
License: UNKNOWN
Keywords: Mass Spectrometry,fasta,Analitical Chemistry,Amino acids
Platform: UNKNOWN
Classifier: Development Status :: 3 - Alpha
Classifier: License :: OSI Approved :: BSD License
Classifier: Intended Audience :: Science/Research
Classifier: Topic :: Scientific/Engineering :: Chemistry
Classifier: Programming Language :: Python :: 3.7
Classifier: Programming Language :: Python :: 3.6
Classifier: Programming Language :: Python :: 3.5
